pytest_isolated/__init__.py
pytest_isolated/plugin.py
pytest_isolated/py.typed
pytest_isolated-0.4.0.dist-info/licenses/LICENSE
pytest_isolated-0.4.0.dist-info/METADATA
pytest_isolated-0.4.0.dist-info/WHEEL
pytest_isolated-0.4.0.dist-info/entry_points.txt
pytest_isolated-0.4.0.dist-info/top_level.txt
pytest_isolated-0.4.0.dist-info/RECORD
