Metadata-Version: 2.4
Name: pytest-isolated
Version: 0.4.0
Summary: Run marked pytest tests in grouped subprocesses (cross-platform).
Author: pytest-isolated contributors
License-Expression: MIT
Project-URL: Homepage, https://github.com/dyollb/pytest-isolated
Project-URL: Repository, https://github.com/dyollb/pytest-isolated
Project-URL: Issues, https://github.com/dyollb/pytest-isolated/issues
Classifier: Development Status :: 4 - Beta
Classifier: Framework :: Pytest
Classifier: Intended Audience :: Developers
Classifier: Operating System :: OS Independent
Classifier: Programming Language :: Python :: 3
Classifier: Programming Language :: Python :: 3.11
Classifier: Programming Language :: Python :: 3.12
Classifier: Topic :: Software Development :: Testing
Requires-Python: >=3.11
License-File: LICENSE
Requires-Dist: pytest>=7.0
Provides-Extra: dev
Requires-Dist: pre-commit; extra == "dev"
Requires-Dist: build; extra == "dev"
Requires-Dist: ruff; extra == "dev"
Provides-Extra: test
Requires-Dist: pytest-timeout; extra == "test"
Dynamic: license-file
